gitsort/__init__.py
gitsort/cli.py
gitsort/sorters.py
gitsort/table.py
gitsort/utils.py
gitsort-0.1.dev0.dist-info/LICENSE
gitsort-0.1.dev0.dist-info/METADATA
gitsort-0.1.dev0.dist-info/WHEEL
gitsort-0.1.dev0.dist-info/entry_points.txt
gitsort-0.1.dev0.dist-info/top_level.txt
gitsort-0.1.dev0.dist-info/RECORD
