Metadata-Version: 2.1
Name: gitsort
Version: 0.1.dev0
Summary: Sort various Github things
Home-page: UNKNOWN
Author: UNKNOWN
Author-email: UNKNOWN
License: UNKNOWN
Platform: UNKNOWN
